LICENSE
naif_leapseconds/__init__.py
naif_leapseconds/compare.py
naif_leapseconds/fetch.py
naif_leapseconds/latest_leapseconds.md5
naif_leapseconds/latest_leapseconds.tls
naif_leapseconds/tests/__init__.py
naif_leapseconds/tests/test_compare.py
naif_leapseconds/tests/test_naif_leapseconds.py
naif_leapseconds-2025.4.22.dist-info/licenses/LICENSE
naif_leapseconds-2025.4.22.dist-info/METADATA
naif_leapseconds-2025.4.22.dist-info/WHEEL
naif_leapseconds-2025.4.22.dist-info/top_level.txt
naif_leapseconds-2025.4.22.dist-info/RECORD
