Metadata-Version: 2.4
Name: naif_leapseconds
Version: 2025.4.22
Summary: NAIF Leapseconds Kernel for SPICE
Author-email: B612 Asteroid Institute <info@b612foundation.org>
License: MIT License
Requires-Python: >=3.7
License-File: LICENSE
Provides-Extra: tests
Requires-Dist: pytest; extra == "tests"
Requires-Dist: spiceypy; extra == "tests"
Dynamic: license-file
